{
	"format_version": "1.12.0",
	"minecraft:geometry": [
		{
			"description": {
				"identifier": "geometry.unknown",
				"texture_width": 64,
				"texture_height": 64,
				"visible_bounds_width": 10,
				"visible_bounds_height": 4.5,
				"visible_bounds_offset": [0, 1.75, 0]
			},
			"bones": [
				{
					"name": "Body",
					"pivot": [0, 3, 8.25]
				},
				{
					"name": "UpperBody",
					"parent": "Body",
					"pivot": [0, -3.96232, -1.29574],
					"rotation": [-5, 0, 0]
				},
				{
					"name": "Body1",
					"parent": "UpperBody",
					"pivot": [0, -3.96232, -1.29574]
				},
				{
					"name": "Body2",
					"parent": "Body1",
					"pivot": [0, -3.96232, -1.29574]
				},
				{
					"name": "Front",
					"parent": "Body2",
					"pivot": [0, -3.96232, -1.29574],
					"cubes": [
						{
							"origin": [-0.80989, 5.26618, -5.34075],
							"size": [1.61979, 2.36455, 2.85731],
							"pivot": [0, -2.76882, -0.517],
							"rotation": [-10, 0, 0],
							"uv": {
								"north": {"uv": [2, 28], "uv_size": [1.5, 2.5]},
								"east": {"uv": [16, 17], "uv_size": [3, 2.5]},
								"south": {"uv": [28, 3], "uv_size": [1.5, 2.5]},
								"west": {"uv": [7, 19], "uv_size": [3, 2.5]},
								"up": {"uv": [12, 25], "uv_size": [1.5, 3]},
								"down": {"uv": [25, 19], "uv_size": [1.5, -3]}
							}
						},
						{
							"origin": [-1.58864, 6.13868, -6.24198],
							"size": [3.17727, 3.25454, 4.6048],
							"pivot": [0, -3.21382, -0.517],
							"rotation": [2.5, 0, 0],
							"uv": {
								"north": {"uv": [12, 10], "uv_size": [3, 3.5]},
								"east": {"uv": [0, 0], "uv_size": [4.5, 3.5]},
								"south": {"uv": [0, 13], "uv_size": [3, 3.5]},
								"west": {"uv": [0, 4], "uv_size": [4.5, 3.5]},
								"up": {"uv": [8, 6], "uv_size": [3, 4.5]},
								"down": {"uv": [10, 4.5], "uv_size": [3, -4.5]}
							}
						}
					]
				},
				{
					"name": "Hips",
					"parent": "Body2",
					"pivot": [0, -4.07357, -0.517],
					"cubes": [
						{
							"origin": [-1.47739, 6.06243, -3.00452],
							"size": [2.95477, 3.23704, 4.9973],
							"uv": {
								"north": {"uv": [14, 6], "uv_size": [3, 3]},
								"east": {"uv": [5, 0], "uv_size": [5, 3]},
								"south": {"uv": [12, 14], "uv_size": [3, 3]},
								"west": {"uv": [5, 3], "uv_size": [5, 3]},
								"up": {"uv": [5, 6], "uv_size": [3, 5]},
								"down": {"uv": [0, 13], "uv_size": [3, -5]}
							}
						},
						{
							"origin": [-0.92114, 5.00494, 2.00168],
							"size": [1.84228, 2.31955, 2.99482],
							"pivot": [0, -2.76882, -0.517],
							"rotation": [22.5, 0, 0],
							"uv": {
								"north": {"uv": [16, 24], "uv_size": [2, 2.5]},
								"east": {"uv": [10, 17], "uv_size": [3, 2.5]},
								"south": {"uv": [24, 19], "uv_size": [2, 2.5]},
								"west": {"uv": [13, 17], "uv_size": [3, 2.5]},
								"up": {"uv": [3, 8], "uv_size": [2, 3]},
								"down": {"uv": [22, 23], "uv_size": [2, -3]}
							}
						}
					]
				},
				{
					"name": "Arms",
					"parent": "UpperBody",
					"pivot": [0, -2.40483, -1.29574]
				},
				{
					"name": "LeftArm",
					"parent": "Arms",
					"pivot": [0, -2.62733, -1.07324]
				},
				{
					"name": "UpperL",
					"parent": "LeftArm",
					"pivot": [0, -2.62733, -1.07324],
					"cubes": [
						{
							"origin": [1.08134, 5.19438, -6.91381],
							"size": [1.21261, 2.38518, 1.93017],
							"pivot": [-0.58628, -2.32383, -0.85074],
							"rotation": [-4.99527, -0.21782, -2.4905],
							"uv": {
								"north": {"uv": [30, 8], "uv_size": [1, 2.5]},
								"east": {"uv": [24, 3], "uv_size": [2, 2.5]},
								"south": {"uv": [30, 11], "uv_size": [1, 2.5]},
								"west": {"uv": [14, 24], "uv_size": [2, 2.5]},
								"up": {"uv": [13, 3], "uv_size": [1, 2]},
								"down": {"uv": [6, 22], "uv_size": [1, -2]}
							}
						}
					]
				},
				{
					"name": "ForeL",
					"parent": "LeftArm",
					"pivot": [-0.58628, -3.18358, -0.85074],
					"cubes": [
						{
							"origin": [0.99012, -4.8247, 7.51073],
							"size": [0.84883, 2.17269, 1.12888],
							"pivot": [-0.58628, -2.32383, -0.85074],
							"rotation": [130, 0, 0],
							"uv": {
								"north": {"uv": [24, 6], "uv_size": [1, 2]},
								"east": {"uv": [30, 27], "uv_size": [1, 2]},
								"south": {"uv": [30, 29], "uv_size": [1, 2]},
								"west": {"uv": [0, 31], "uv_size": [1, 2]},
								"up": {"uv": [11, 32], "uv_size": [1, 1]},
								"down": {"uv": [32, 14], "uv_size": [1, -1]}
							}
						}
					]
				},
				{
					"name": "WristL",
					"parent": "LeftArm",
					"pivot": [-0.58628, -3.18358, -0.85074],
					"cubes": [
						{
							"origin": [1.11138, -11.20675, 0.32486],
							"size": [0.60631, 1.97771, 0.96008],
							"pivot": [-0.58628, -2.88007, -2.29698],
							"rotation": [-175, 0, 0],
							"uv": {
								"north": {"uv": [14, 32], "uv_size": [0.5, 2]},
								"east": {"uv": [1, 31], "uv_size": [1, 2]},
								"south": {"uv": [32, 14], "uv_size": [0.5, 2]},
								"west": {"uv": [2, 31], "uv_size": [1, 2]},
								"up": {"uv": [32, 26], "uv_size": [0.5, 1]},
								"down": {"uv": [32, 28], "uv_size": [0.5, -1]}
							}
						}
					]
				},
				{
					"name": "HandL",
					"parent": "LeftArm",
					"pivot": [-0.58628, -3.73982, -2.29698],
					"cubes": [
						{
							"origin": [0.85683, 1.9408, -6.6814],
							"size": [0.84883, 1.69766, 0.48505],
							"pivot": [1.31446, 2.63118, -6.06219],
							"rotation": [-152.21957, 3.95768, 8.10282],
							"uv": {
								"north": {"uv": [31, 31], "uv_size": [1, 1.5]},
								"east": {"uv": [32, 22], "uv_size": [0.5, 1.5]},
								"south": {"uv": [32, 0], "uv_size": [1, 1.5]},
								"west": {"uv": [24, 32], "uv_size": [0.5, 1.5]},
								"up": {"uv": [28, 32], "uv_size": [1, 0.5]},
								"down": {"uv": [32, 28.5], "uv_size": [1, -0.5]}
							}
						}
					]
				},
				{
					"name": "RightArm",
					"parent": "Arms",
					"pivot": [0, -2.62733, -1.07324]
				},
				{
					"name": "UpperR",
					"parent": "RightArm",
					"pivot": [-1.30552, 6.88869, -5.16221],
					"cubes": [
						{
							"origin": [-2.29395, 5.19438, -6.91381],
							"size": [1.21261, 2.38518, 1.93017],
							"pivot": [0.58628, -2.32383, -0.85074],
							"rotation": [-4.99527, 0.21782, 2.4905],
							"uv": {
								"north": {"uv": [12, 30], "uv_size": [1, 2.5]},
								"east": {"uv": [24, 22], "uv_size": [2, 2.5]},
								"south": {"uv": [13, 30], "uv_size": [1, 2.5]},
								"west": {"uv": [2, 25], "uv_size": [2, 2.5]},
								"up": {"uv": [3, 31], "uv_size": [1, 2]},
								"down": {"uv": [31, 8], "uv_size": [1, -2]}
							}
						}
					]
				},
				{
					"name": "ForeR",
					"parent": "RightArm",
					"pivot": [0.58628, -3.18358, -0.85074],
					"cubes": [
						{
							"origin": [-1.83895, -4.8247, 7.51073],
							"size": [0.84883, 2.17269, 1.12888],
							"pivot": [0.58628, -2.32383, -0.85074],
							"rotation": [130, 0, 0],
							"uv": {
								"north": {"uv": [31, 8], "uv_size": [1, 2]},
								"east": {"uv": [31, 10], "uv_size": [1, 2]},
								"south": {"uv": [31, 12], "uv_size": [1, 2]},
								"west": {"uv": [31, 14], "uv_size": [1, 2]},
								"up": {"uv": [15, 32], "uv_size": [1, 1]},
								"down": {"uv": [16, 33], "uv_size": [1, -1]}
							}
						}
					]
				},
				{
					"name": "WristR",
					"parent": "RightArm",
					"pivot": [0.58628, -3.18358, -0.85074],
					"cubes": [
						{
							"origin": [-1.71768, -11.20675, 0.32486],
							"size": [0.60631, 1.97771, 0.96008],
							"pivot": [0.58628, -2.88007, -2.29698],
							"rotation": [-175, 0, 0],
							"uv": {
								"north": {"uv": [32, 16], "uv_size": [0.5, 2]},
								"east": {"uv": [31, 16], "uv_size": [1, 2]},
								"south": {"uv": [17, 32], "uv_size": [0.5, 2]},
								"west": {"uv": [22, 31], "uv_size": [1, 2]},
								"up": {"uv": [29, 32], "uv_size": [0.5, 1]},
								"down": {"uv": [32, 30], "uv_size": [0.5, -1]}
							}
						}
					]
				},
				{
					"name": "HandR",
					"parent": "RightArm",
					"pivot": [0.58628, -3.73982, -2.29698],
					"cubes": [
						{
							"origin": [-1.70566, 1.9408, -6.6814],
							"size": [0.84883, 1.69766, 0.48505],
							"pivot": [-1.31446, 2.63118, -6.06219],
							"rotation": [-152.21957, -3.95768, -8.10282],
							"uv": {
								"north": {"uv": [32, 2], "uv_size": [1, 1.5]},
								"east": {"uv": [32, 24], "uv_size": [0.5, 1.5]},
								"south": {"uv": [4, 32], "uv_size": [1, 1.5]},
								"west": {"uv": [25, 32], "uv_size": [0.5, 1.5]},
								"up": {"uv": [32, 30], "uv_size": [1, 0.5]},
								"down": {"uv": [32, 31.5], "uv_size": [1, -0.5]}
							}
						}
					]
				},
				{
					"name": "Tail",
					"parent": "UpperBody",
					"pivot": [0, -3.18358, -0.7395],
					"rotation": [5, 0, 0]
				},
				{
					"name": "1",
					"parent": "Tail",
					"pivot": [0, 7.41046, 3.59922],
					"cubes": [
						{
							"origin": [-1.33499, 6.1136, 2.70922],
							"size": [2.66998, 2.79872, 2.80498],
							"uv": {
								"north": {"uv": [7, 16], "uv_size": [2.5, 3]},
								"east": {"uv": [13, 0], "uv_size": [3, 3]},
								"south": {"uv": [0, 17], "uv_size": [2.5, 3]},
								"west": {"uv": [14, 3], "uv_size": [3, 3]},
								"up": {"uv": [17, 2], "uv_size": [2.5, 3]},
								"down": {"uv": [17, 8], "uv_size": [2.5, -3]}
							}
						}
					]
				},
				{
					"name": "2",
					"parent": "1",
					"pivot": [0, 7.77905, 5.57336],
					"rotation": [-5, 0, 0],
					"cubes": [
						{
							"origin": [-1.11249, 5.4811, 5.7892],
							"size": [2.22498, 2.44748, 3.39622],
							"pivot": [0, -3.08507, -0.7395],
							"rotation": [7.5, 0, 0],
							"uv": {
								"north": {"uv": [23, 10], "uv_size": [2, 2.5]},
								"east": {"uv": [15, 9], "uv_size": [3.5, 2.5]},
								"south": {"uv": [23, 16], "uv_size": [2, 2.5]},
								"west": {"uv": [15, 12], "uv_size": [3.5, 2.5]},
								"up": {"uv": [19, 8], "uv_size": [2, 3.5]},
								"down": {"uv": [19, 15.5], "uv_size": [2, -3.5]}
							}
						}
					]
				},
				{
					"name": "3",
					"parent": "2",
					"pivot": [0, 8.07966, 7.37703],
					"cubes": [
						{
							"origin": [-1.00124, 6.03735, 7.27043],
							"size": [2.00248, 2.22498, 3.36123],
							"pivot": [0, -3.08507, -0.7395],
							"rotation": [5, 0, 0],
							"uv": {
								"north": {"uv": [25, 12], "uv_size": [2, 2]},
								"east": {"uv": [19, 16], "uv_size": [3.5, 2]},
								"south": {"uv": [24, 25], "uv_size": [2, 2]},
								"west": {"uv": [19, 18], "uv_size": [3.5, 2]},
								"up": {"uv": [0, 20], "uv_size": [2, 3.5]},
								"down": {"uv": [20, 3.5], "uv_size": [2, -3.5]}
							}
						}
					]
				},
				{
					"name": "4",
					"parent": "3",
					"pivot": [0, 10.77352, 9.76308],
					"cubes": [
						{
							"origin": [-0.88999, 6.70484, 8.71667],
							"size": [1.77998, 1.89123, 3.80622],
							"pivot": [0, -3.08507, -0.7395],
							"rotation": [2.5, 0, 0],
							"uv": {
								"north": {"uv": [26, 0], "uv_size": [2, 2]},
								"east": {"uv": [15, 15], "uv_size": [4, 2]},
								"south": {"uv": [26, 2], "uv_size": [2, 2]},
								"west": {"uv": [16, 0], "uv_size": [4, 2]},
								"up": {"uv": [3, 16], "uv_size": [2, 4]},
								"down": {"uv": [5, 20], "uv_size": [2, -4]}
							}
						}
					]
				},
				{
					"name": "5",
					"parent": "4",
					"pivot": [0, -3.94482, -0.7395],
					"cubes": [
						{
							"origin": [-0.77874, 7.37233, 10.49665],
							"size": [1.55749, 1.66873, 3.80622],
							"uv": {
								"north": {"uv": [30, 4], "uv_size": [1.5, 1.5]},
								"east": {"uv": [20, 4], "uv_size": [4, 1.5]},
								"south": {"uv": [14, 30], "uv_size": [1.5, 1.5]},
								"west": {"uv": [20, 6], "uv_size": [4, 1.5]},
								"up": {"uv": [14, 20], "uv_size": [1.5, 4]},
								"down": {"uv": [16, 24], "uv_size": [1.5, -4]}
							}
						}
					]
				},
				{
					"name": "6",
					"parent": "5",
					"pivot": [0, -3.94482, -0.7395],
					"cubes": [
						{
							"origin": [-0.66749, 7.59483, 12.72163],
							"size": [1.33499, 1.33499, 4.02872],
							"uv": {
								"north": {"uv": [16, 30], "uv_size": [1.5, 1.5]},
								"east": {"uv": [18, 20], "uv_size": [4, 1.5]},
								"south": {"uv": [18, 30], "uv_size": [1.5, 1.5]},
								"west": {"uv": [21, 8], "uv_size": [4, 1.5]},
								"up": {"uv": [21, 10], "uv_size": [1.5, 4]},
								"down": {"uv": [22, 4], "uv_size": [1.5, -4]}
							}
						}
					]
				},
				{
					"name": "7",
					"parent": "6",
					"pivot": [0, -3.94482, -0.7395],
					"cubes": [
						{
							"origin": [-0.55624, 8.57858, 14.72411],
							"size": [1.11249, 0.90749, 5.32871],
							"pivot": [0, -3.08507, -0.7395],
							"rotation": [-2.5, 0, 0],
							"uv": {
								"north": {"uv": [10, 5], "uv_size": [1, 1]},
								"east": {"uv": [21, 14], "uv_size": [5.5, 1]},
								"south": {"uv": [11, 10], "uv_size": [1, 1]},
								"west": {"uv": [21, 15], "uv_size": [5.5, 1]},
								"up": {"uv": [22, 23], "uv_size": [1, 5.5]},
								"down": {"uv": [23, 28.5], "uv_size": [1, -5.5]}
							}
						}
					]
				},
				{
					"name": "Neck",
					"parent": "UpperBody",
					"pivot": [0, -2.55734, -2.93574],
					"rotation": [-10, 0, 0]
				},
				{
					"name": "Base",
					"parent": "Neck",
					"pivot": [0, 7.50724, -8.73733],
					"cubes": [
						{
							"origin": [-1.11249, 2.06738, -12.16941],
							"size": [2.22498, 2.68747, 1.55749],
							"pivot": [0, -1.25259, -1.82325],
							"rotation": [-27.5, 0, 0],
							"uv": {
								"north": {"uv": [0, 24], "uv_size": [2, 2.5]},
								"east": {"uv": [14, 27], "uv_size": [1.5, 2.5]},
								"south": {"uv": [24, 0], "uv_size": [2, 2.5]},
								"west": {"uv": [27, 14], "uv_size": [1.5, 2.5]},
								"up": {"uv": [12, 28], "uv_size": [2, 1.5]},
								"down": {"uv": [18, 29.5], "uv_size": [2, -1.5]}
							}
						},
						{
							"origin": [-0.88999, -1.04759, -16.73061],
							"size": [1.77998, 2.24248, 2.22498],
							"pivot": [0, -3.36632, -3.38074],
							"rotation": [-47.5, 0, 0],
							"uv": {
								"north": {"uv": [26, 4], "uv_size": [2, 2]},
								"east": {"uv": [6, 26], "uv_size": [2, 2]},
								"south": {"uv": [8, 26], "uv_size": [2, 2]},
								"west": {"uv": [18, 26], "uv_size": [2, 2]},
								"up": {"uv": [26, 19], "uv_size": [2, 2]},
								"down": {"uv": [20, 28], "uv_size": [2, -2]}
							}
						}
					]
				},
				{
					"name": "Neck2",
					"parent": "Neck",
					"pivot": [0, 9.51212, -10.51486],
					"cubes": [
						{
							"origin": [-0.77874, 8.58535, -11.5011],
							"size": [1.55749, 2.01998, 2.11373],
							"pivot": [0, 9.49284, -10.44423],
							"rotation": [-55, 0, 0],
							"uv": {
								"north": {"uv": [28, 19], "uv_size": [1.5, 2]},
								"east": {"uv": [26, 21], "uv_size": [2, 2]},
								"south": {"uv": [20, 28], "uv_size": [1.5, 2]},
								"west": {"uv": [26, 23], "uv_size": [2, 2]},
								"up": {"uv": [28, 21], "uv_size": [1.5, 2]},
								"down": {"uv": [28, 25], "uv_size": [1.5, -2]}
							}
						}
					]
				},
				{
					"name": "Connection",
					"parent": "Neck",
					"pivot": [0, 10.15832, -11.24163],
					"cubes": [
						{
							"origin": [-0.66749, 9.31723, -12.4282],
							"size": [1.33499, 1.79748, 2.24248],
							"pivot": [0, 10.11347, -11.40946],
							"rotation": [-5, 0, 0],
							"uv": {
								"north": {"uv": [28, 25], "uv_size": [1.5, 2]},
								"east": {"uv": [26, 25], "uv_size": [2, 2]},
								"south": {"uv": [28, 27], "uv_size": [1.5, 2]},
								"west": {"uv": [0, 27], "uv_size": [2, 2]},
								"up": {"uv": [0, 29], "uv_size": [1.5, 2]},
								"down": {"uv": [29, 8], "uv_size": [1.5, -2]}
							}
						},
						{
							"origin": [-0.445, 4.05236, -17.73186],
							"size": [0.88999, 1.14749, 3.55997],
							"pivot": [0, -1.92009, -4.15948],
							"rotation": [-27.5, 0, 0],
							"uv": {
								"north": {"uv": [14, 9], "uv_size": [1, 1]},
								"east": {"uv": [27, 17], "uv_size": [3.5, 1]},
								"south": {"uv": [16, 2], "uv_size": [1, 1]},
								"west": {"uv": [27, 18], "uv_size": [3.5, 1]},
								"up": {"uv": [4, 28], "uv_size": [1, 3.5]},
								"down": {"uv": [5, 31.5], "uv_size": [1, -3.5]}
							}
						}
					]
				},
				{
					"name": "Head",
					"parent": "Neck",
					"pivot": [0, 10.14542, -12.81532],
					"rotation": [17.5, 0, 0],
					"cubes": [
						{
							"origin": [-0.80099, -14.95869, -21.2154],
							"size": [1.60199, 1.56639, 1.70848],
							"pivot": [0, -6.00982, -3.93651],
							"rotation": [-87.5, 0, 0],
							"uv": {
								"north": {"uv": [30, 19], "uv_size": [1.5, 1.5]},
								"east": {"uv": [20, 30], "uv_size": [1.5, 1.5]},
								"south": {"uv": [30, 21], "uv_size": [1.5, 1.5]},
								"west": {"uv": [30, 23], "uv_size": [1.5, 1.5]},
								"up": {"uv": [24, 30], "uv_size": [1.5, 1.5]},
								"down": {"uv": [30, 26.5], "uv_size": [1.5, -1.5]}
							}
						}
					]
				},
				{
					"name": "Jaw",
					"parent": "Head",
					"pivot": [0, -6.86957, -3.93651],
					"cubes": [
						{
							"origin": [-0.77429, -16.64492, -21.54915],
							"size": [1.54859, 4.03136, 1.04099],
							"pivot": [0, -6.00982, -3.93651],
							"rotation": [-85, 0, 0],
							"uv": {
								"north": {"uv": [6, 22], "uv_size": [1.5, 4]},
								"east": {"uv": [27, 6], "uv_size": [1, 4]},
								"south": {"uv": [8, 22], "uv_size": [1.5, 4]},
								"west": {"uv": [27, 10], "uv_size": [1, 4]},
								"up": {"uv": [10, 16], "uv_size": [1.5, 1]},
								"down": {"uv": [17, 9], "uv_size": [1.5, -1]}
							}
						}
					]
				},
				{
					"name": "Bottom",
					"parent": "Jaw",
					"pivot": [0, 9.52935, -13.8567],
					"cubes": [
						{
							"origin": [-0.64969, -17.26792, -20.18381],
							"size": [1.29939, 3.78216, 0.54784],
							"pivot": [0, -6.00982, -3.93651],
							"rotation": [-87.5, 0, 0],
							"uv": {
								"north": {"uv": [18, 22], "uv_size": [1.5, 4]},
								"east": {"uv": [26, 30], "uv_size": [0.5, 4]},
								"south": {"uv": [20, 22], "uv_size": [1.5, 4]},
								"west": {"uv": [27, 30], "uv_size": [0.5, 4]},
								"up": {"uv": [18, 32], "uv_size": [1.5, 0.5]},
								"down": {"uv": [32, 18.5], "uv_size": [1.5, -0.5]}
							}
						}
					]
				},
				{
					"name": "Legs",
					"parent": "Body",
					"pivot": [0, -3.57732, -2.03323]
				},
				{
					"name": "Right",
					"parent": "Legs",
					"pivot": [0, 7.45556, 0.9635]
				},
				{
					"name": "Thigh",
					"parent": "Right",
					"pivot": [-1.33499, 6.81444, 0.3271],
					"cubes": [
						{
							"origin": [-2.00248, 6.96109, -3.51446],
							"size": [1.33499, 3.62997, 2.25998],
							"pivot": [-2.78122, -0.49259, -6.59443],
							"rotation": [-20, 0, 0],
							"uv": {
								"north": {"uv": [2, 20], "uv_size": [1.5, 4.5]},
								"east": {"uv": [3, 11], "uv_size": [2.5, 4.5]},
								"south": {"uv": [4, 20], "uv_size": [1.5, 4.5]},
								"west": {"uv": [11, 5], "uv_size": [2.5, 4.5]},
								"up": {"uv": [16, 27], "uv_size": [1.5, 2.5]},
								"down": {"uv": [24, 29.5], "uv_size": [1.5, -2.5]}
							}
						}
					]
				},
				{
					"name": "Leg1R",
					"parent": "Thigh",
					"pivot": [-1.33499, 4.81581, 0.32707],
					"cubes": [
						{
							"origin": [-1.89123, 1.2874, 3.28923],
							"size": [1.11249, 2.78122, 1.68623],
							"pivot": [-2.78122, -3.16256, -1.81073],
							"rotation": [30, 0, 0],
							"uv": {
								"north": {"uv": [29, 8], "uv_size": [1, 3]},
								"east": {"uv": [4, 25], "uv_size": [1.5, 3]},
								"south": {"uv": [29, 11], "uv_size": [1, 3]},
								"west": {"uv": [25, 6], "uv_size": [1.5, 3]},
								"up": {"uv": [23, 31], "uv_size": [1, 1.5]},
								"down": {"uv": [31, 28.5], "uv_size": [1, -1.5]}
							}
						}
					]
				},
				{
					"name": "Leg2R",
					"parent": "Right",
					"pivot": [-1.33499, 2.62238, 0.9705],
					"cubes": [
						{
							"origin": [-1.77998, 0.95365, 0.41425],
							"size": [0.88999, 3.33747, 1.11249],
							"uv": {
								"north": {"uv": [6, 28], "uv_size": [1, 3.5]},
								"east": {"uv": [28, 6], "uv_size": [1, 3.5]},
								"south": {"uv": [7, 28], "uv_size": [1, 3.5]},
								"west": {"uv": [8, 28], "uv_size": [1, 3.5]},
								"up": {"uv": [23, 13], "uv_size": [1, 1]},
								"down": {"uv": [23, 20], "uv_size": [1, -1]}
							}
						}
					]
				},
				{
					"name": "AnkleR",
					"parent": "Leg2R",
					"pivot": [-1.33499, 0.86352, 0.84943],
					"cubes": [
						{
							"origin": [-1.89123, 0.6199, -0.03074],
							"size": [1.11249, 1.00124, 1.11249],
							"pivot": [-2.78122, -2.71757, -2.25572],
							"rotation": [-5, 0, 0],
							"uv": {
								"north": {"uv": [24, 13], "uv_size": [1, 1]},
								"east": {"uv": [29, 16], "uv_size": [1, 1]},
								"south": {"uv": [30, 16], "uv_size": [1, 1]},
								"west": {"uv": [31, 18], "uv_size": [1, 1]},
								"up": {"uv": [32, 4], "uv_size": [1, 1]},
								"down": {"uv": [5, 33], "uv_size": [1, -1]}
							}
						}
					]
				},
				{
					"name": "FootR",
					"parent": "AnkleR",
					"pivot": [-1.33499, 0.28615, 0.02488],
					"cubes": [
						{
							"origin": [-2.00248, -0.04759, -0.92074],
							"size": [1.33499, 0.66749, 1.89123],
							"uv": {
								"north": {"uv": [32, 19], "uv_size": [1.5, 0.5]},
								"east": {"uv": [32, 5], "uv_size": [2, 0.5]},
								"south": {"uv": [20, 32], "uv_size": [1.5, 0.5]},
								"west": {"uv": [6, 32], "uv_size": [2, 0.5]},
								"up": {"uv": [29, 14], "uv_size": [1.5, 2]},
								"down": {"uv": [22, 31], "uv_size": [1.5, -2]}
							}
						}
					]
				},
				{
					"name": "ClawR",
					"parent": "FootR",
					"pivot": [-0.77874, 0.62909, 0.54232]
				},
				{
					"name": "Left",
					"parent": "Legs",
					"pivot": [0, 7.45556, 0.9635]
				},
				{
					"name": "ThighL",
					"parent": "Left",
					"pivot": [1.33499, 6.81444, 0.3271],
					"cubes": [
						{
							"origin": [0.66749, 6.96109, -3.51446],
							"size": [1.33499, 3.62997, 2.25998],
							"pivot": [2.78122, -0.49259, -6.59443],
							"rotation": [-20, 0, 0],
							"uv": {
								"north": {"uv": [10, 20], "uv_size": [1.5, 4.5]},
								"east": {"uv": [6, 11], "uv_size": [2.5, 4.5]},
								"south": {"uv": [12, 20], "uv_size": [1.5, 4.5]},
								"west": {"uv": [9, 11], "uv_size": [2.5, 4.5]},
								"up": {"uv": [26, 27], "uv_size": [1.5, 2.5]},
								"down": {"uv": [28, 2.5], "uv_size": [1.5, -2.5]}
							}
						}
					]
				},
				{
					"name": "Leg1L",
					"parent": "ThighL",
					"pivot": [2.78122, -1.35234, -6.59443],
					"cubes": [
						{
							"origin": [0.77874, 1.2874, 3.28923],
							"size": [1.11249, 2.78122, 1.68623],
							"pivot": [2.78122, -3.16256, -1.81073],
							"rotation": [30, 0, 0],
							"uv": {
								"north": {"uv": [28, 29], "uv_size": [1, 3]},
								"east": {"uv": [25, 9], "uv_size": [1.5, 3]},
								"south": {"uv": [29, 29], "uv_size": [1, 3]},
								"west": {"uv": [10, 25], "uv_size": [1.5, 3]},
								"up": {"uv": [31, 29], "uv_size": [1, 1.5]},
								"down": {"uv": [30, 32.5], "uv_size": [1, -1.5]}
							}
						}
					]
				},
				{
					"name": "Leg2L",
					"parent": "Left",
					"pivot": [2.78122, -3.64655, -3.01318],
					"cubes": [
						{
							"origin": [0.88999, 0.96345, 0.40952],
							"size": [0.88999, 3.33747, 1.11249],
							"uv": {
								"north": {"uv": [9, 28], "uv_size": [1, 3.5]},
								"east": {"uv": [10, 28], "uv_size": [1, 3.5]},
								"south": {"uv": [28, 10], "uv_size": [1, 3.5]},
								"west": {"uv": [11, 28], "uv_size": [1, 3.5]},
								"up": {"uv": [32, 6], "uv_size": [1, 1]},
								"down": {"uv": [32, 8], "uv_size": [1, -1]}
							}
						}
					]
				},
				{
					"name": "AnkleL",
					"parent": "Leg2L",
					"pivot": [1.33499, 0.87332, 0.8447],
					"cubes": [
						{
							"origin": [0.77874, 0.6297, -0.03547],
							"size": [1.11249, 1.00124, 1.11249],
							"pivot": [2.78122, -2.70777, -2.26045],
							"rotation": [-5, 0, 0],
							"uv": {
								"north": {"uv": [8, 32], "uv_size": [1, 1]},
								"east": {"uv": [32, 8], "uv_size": [1, 1]},
								"south": {"uv": [9, 32], "uv_size": [1, 1]},
								"west": {"uv": [32, 9], "uv_size": [1, 1]},
								"up": {"uv": [10, 32], "uv_size": [1, 1]},
								"down": {"uv": [32, 11], "uv_size": [1, -1]}
							}
						}
					]
				},
				{
					"name": "FootL",
					"parent": "AnkleL",
					"pivot": [1.33499, 0.2851, 0.00492],
					"cubes": [
						{
							"origin": [0.66749, -0.04864, -0.9407],
							"size": [1.33499, 0.66749, 1.89123],
							"uv": {
								"north": {"uv": [32, 20], "uv_size": [1.5, 0.5]},
								"east": {"uv": [32, 11], "uv_size": [2, 0.5]},
								"south": {"uv": [32, 21], "uv_size": [1.5, 0.5]},
								"west": {"uv": [32, 12], "uv_size": [2, 0.5]},
								"up": {"uv": [30, 0], "uv_size": [1.5, 2]},
								"down": {"uv": [30, 4], "uv_size": [1.5, -2]}
							}
						}
					]
				},
				{
					"name": "ClawL",
					"parent": "FootL",
					"pivot": [0.77874, 0.45846, 0.30653]
				}
			]
		}
	]
}